fastapi_utils/__init__.py
fastapi_utils/exceptions.py
fastapi_utils/filters/__init__.py
fastapi_utils/filters/base.py
fastapi_utils/filters/ordering_filter.py
fastapi_utils/filters/search_filter.py
fastapi_utils/pagination/__init__.py
fastapi_utils/pagination/base.py
fastapi_utils/pagination/limit_pagination.py
fastapi_utils/pagination/page.py
fastapi_utils/pagination/page_pagination.py
fastapi_utils/schemas/__init__.py
fastapi_utils/schemas/default_schemas.py
fastapi_utils/serializers/__init__.py
fastapi_utils/serializers/base.py
fastapi_utils/serializers/serializers.py
fastapi_utils/serializers/sqlalchemy/__init__.py
fastapi_utils/serializers/sqlalchemy/serializers.py
fastapi_utils/serializers/tortoise/__init__.py
fastapi_utils/serializers/tortoise/serializers.py
fastapi_utils/utils/__init__.py
fastapi_utils/utils/utils.py
utils_fastapi-0.0.7.dist-info/METADATA
utils_fastapi-0.0.7.dist-info/WHEEL
utils_fastapi-0.0.7.dist-info/RECORD
