Metadata-Version: 2.3
Name: utils_fastapi
Version: 0.0.7
Summary: Utils for FastApi. Filters, Pagination, Serializers, Schemas
Project-URL: Source, https://github.com/zayycev22/fastapi-utils
Author: zayycev22
Classifier: Framework :: FastAPI
Classifier: License :: OSI Approved :: MIT License
Classifier: Operating System :: OS Independent
Classifier: Programming Language :: Python :: 3 :: Only
Classifier: Programming Language :: Python :: 3.10
Classifier: Programming Language :: Python :: 3.11
Classifier: Programming Language :: Python :: 3.12
Requires-Python: >=3.10
Requires-Dist: fastapi>=0.110.0
Requires-Dist: ordered-set>=4.1.0
Requires-Dist: pydantic>=2.6.3
Provides-Extra: sqlalchemy
Requires-Dist: greenlet>=3.0.0; extra == 'sqlalchemy'
Requires-Dist: sqlalchemy>=2.0.0; extra == 'sqlalchemy'
Requires-Dist: typing-extensions; extra == 'sqlalchemy'
Provides-Extra: tortoise
Requires-Dist: tortoise-orm; extra == 'tortoise'
Requires-Dist: typing-extensions; extra == 'tortoise'
